cubicweb_person/__init__.py
cubicweb_person/__pkginfo__.py
cubicweb_person/entities.py
cubicweb_person/hooks.py
cubicweb_person/schema.py
cubicweb_person/views.py
cubicweb_person/data/icon_person.gif
cubicweb_person/doc/schema.png
cubicweb_person/i18n/en.po
cubicweb_person/i18n/fr.po
cubicweb_person/migration/1.12.0_Any.py
cubicweb_person/migration/1.5.0_Any.py
cubicweb_person/migration/postcreate.py
cubicweb_person-2.1.0.dist-info/METADATA
cubicweb_person-2.1.0.dist-info/WHEEL
cubicweb_person-2.1.0.dist-info/entry_points.txt
cubicweb_person-2.1.0.dist-info/top_level.txt
cubicweb_person-2.1.0.dist-info/RECORD
